x_pyAPI/__init__.py
x_pyAPI/x_pyAPI.py
X_pyAPI-1.2.dist-info/LICENCE
X_pyAPI-1.2.dist-info/METADATA
X_pyAPI-1.2.dist-info/WHEEL
X_pyAPI-1.2.dist-info/top_level.txt
X_pyAPI-1.2.dist-info/RECORD
