Metadata-Version: 2.1
Name: X-pyAPI
Version: 1.2
Summary: A simple Python library for posting tweets on X.com using new X API v2.
Home-page: https://github.com/redianmarku/X-PyAPI.git
Author: Redian Marku
Author-email: redian@topnotch-programmer.com
Classifier: Programming Language :: Python :: 3
Classifier: License :: OSI Approved :: MIT License
Classifier: Operating System :: OS Independent
License-File: LICENCE
Requires-Dist: requests-oauthlib
